[
    {
        "file_name": "eib 2024-01-10 00-20-462.jpg",
        "imageFull-link": "https://i.imgur.com/eduLGQR.jpeg",
        "thumbnail-link": "https://i.imgur.com/PjEDIK9.jpeg",
        "image1080-link": "https://i.imgur.com/icaVfMm.jpeg",
        "aspect-ratio": "2.3333333333333335"
    },
    {
        "file_name": "eib 2024-01-10 00-27-07.jpg",
        "imageFull-link": "https://i.imgur.com/qOTwrBJ.jpeg",
        "thumbnail-link": "https://i.imgur.com/Ag7nypg.jpeg",
        "image1080-link": "https://i.imgur.com/BYpI82W.jpeg",
        "aspect-ratio": "1.7777777777777777"
    },
    {
        "file_name": "eib 2024-01-10 00-30-23.jpg",
        "imageFull-link": "https://i.imgur.com/KCWIupA.jpeg",
        "thumbnail-link": "https://i.imgur.com/9rnukj8.jpeg",
        "image1080-link": "https://i.imgur.com/3ZPdNcI.jpeg",
        "aspect-ratio": "1.7777777777777777"
    },
    {
        "file_name": "eib 2024-01-10 00-32-42.jpg",
        "imageFull-link": "https://i.imgur.com/ZRWnuvc.jpeg",
        "thumbnail-link": "https://i.imgur.com/1xRM5ti.jpeg",
        "image1080-link": "https://i.imgur.com/PEPNVJF.jpeg",
        "aspect-ratio": "0.8"
    },
    {
        "file_name": "eib 2024-01-10 00-33-57.jpg",
        "imageFull-link": "https://i.imgur.com/445nA5f.jpeg",
        "thumbnail-link": "https://i.imgur.com/22KCy4h.jpeg",
        "image1080-link": "https://i.imgur.com/tUoASLK.jpeg",
        "aspect-ratio": "1.7777777777777777"
    },
    {
        "file_name": "eib 2024-01-10 01-08-52.jpg",
        "imageFull-link": "https://i.imgur.com/1ue79JU.jpeg",
        "thumbnail-link": "https://i.imgur.com/9r6kkp3.jpeg",
        "image1080-link": "https://i.imgur.com/3SEk13I.jpeg",
        "aspect-ratio": "0.8"
    },
    {
        "file_name": "eib 2024-01-10 01-29-22.jpg",
        "imageFull-link": "https://i.imgur.com/dv48U5m.jpeg",
        "thumbnail-link": "https://i.imgur.com/vAv77iu.jpeg",
        "image1080-link": "https://i.imgur.com/zC6mcHx.jpeg",
        "aspect-ratio": "1.7777777777777777"
    },
    {
        "file_name": "eib 2024-01-10 01-37-56.jpg",
        "imageFull-link": "https://i.imgur.com/7bIykQe.jpeg",
        "thumbnail-link": "https://i.imgur.com/WoqmPn8.jpeg",
        "image1080-link": "https://i.imgur.com/Ugt28AX.jpeg",
        "aspect-ratio": "2.33125"
    }
]