[
    {
        "file_name": "Dead Space 2023-02-01 18-10-17.jpg",
        "imageFull-link": "https://i.imgur.com/INQdzQu.jpeg",
        "thumbnail-link": "https://i.imgur.com/kVlU0H3.jpeg",
        "image1080-link": "https://i.imgur.com/0fJAKlI.jpeg",
        "aspect-ratio": "0.8"
    },
    {
        "file_name": "Dead Space 2023-02-01 19-25-40.jpg",
        "imageFull-link": "https://i.imgur.com/yJkTEYN.jpeg",
        "thumbnail-link": "https://i.imgur.com/Q6Ax9HR.jpeg",
        "image1080-link": "https://i.imgur.com/23E3naL.jpeg",
        "aspect-ratio": "2.333637192342753"
    },
    {
        "file_name": "Dead Space 2023-02-04 00-53-29.jpg",
        "imageFull-link": "https://i.imgur.com/BiQE8NU.jpeg",
        "thumbnail-link": "https://i.imgur.com/lBwMAS1.jpeg",
        "image1080-link": "https://i.imgur.com/IjkSTYs.jpeg",
        "aspect-ratio": "0.8"
    },
    {
        "file_name": "Dead Space 2023-02-04 01-15-52.jpg",
        "imageFull-link": "https://i.imgur.com/prYJmnj.jpeg",
        "thumbnail-link": "https://i.imgur.com/HIsyMg8.jpeg",
        "image1080-link": "https://i.imgur.com/39ppw4o.jpeg",
        "aspect-ratio": "2.333637192342753"
    },
    {
        "file_name": "Dead Space 2023-02-04 01-58-53.jpg",
        "imageFull-link": "https://i.imgur.com/XweegZi.jpeg",
        "thumbnail-link": "https://i.imgur.com/K8AVqzU.jpeg",
        "image1080-link": "https://i.imgur.com/g7XvhQQ.jpeg",
        "aspect-ratio": "0.8"
    },
    {
        "file_name": "Dead Space 2023-02-04 02-55-55.jpg",
        "imageFull-link": "https://i.imgur.com/fhHFkg6.jpeg",
        "thumbnail-link": "https://i.imgur.com/fsYVoXn.jpeg",
        "image1080-link": "https://i.imgur.com/SvrmQjI.jpeg",
        "aspect-ratio": "0.8"
    },
    {
        "file_name": "Dead Space 2023-02-10 22-40-43.jpg",
        "imageFull-link": "https://i.imgur.com/RqEfa53.jpeg",
        "thumbnail-link": "https://i.imgur.com/DYuhEQy.jpeg",
        "image1080-link": "https://i.imgur.com/rcjtXtm.jpeg",
        "aspect-ratio": "2.333637192342753"
    },
    {
        "file_name": "Dead Space 2023-02-10 23-57-16.jpg",
        "imageFull-link": "https://i.imgur.com/vcozciC.jpeg",
        "thumbnail-link": "https://i.imgur.com/Nj0CXI5.jpeg",
        "image1080-link": "https://i.imgur.com/skG6yov.jpeg",
        "aspect-ratio": "2.333637192342753"
    }
]